potofox.py
Potofox-0.0.1.dist-info/METADATA
Potofox-0.0.1.dist-info/WHEEL
Potofox-0.0.1.dist-info/top_level.txt
Potofox-0.0.1.dist-info/RECORD
