Metadata-Version: 2.1
Name: Potofox
Version: 0.0.1
Summary: a Deep Learning library
Home-page: https://github.com/spe301/Potosnail
Author: Spencer Holley
Author-email: aacjpw@gmail.com
License: UNKNOWN
Platform: UNKNOWN
Classifier: Development Status :: 5 - Production/Stable
Classifier: Intended Audience :: Developers
Classifier: Operating System :: Microsoft :: Windows :: Windows 10
Classifier: License :: OSI Approved :: MIT License
Classifier: Programming Language :: Python :: 3
Requires-Dist: pandas (>=1.1.3)
Requires-Dist: numpy (>=1.18.0)
Requires-Dist: Potosnail (>=0.2.3)
